gen_head/__about__.py
gen_head/__init__.py
gen_head-1.0.0.dist-info/METADATA
gen_head-1.0.0.dist-info/WHEEL
gen_head-1.0.0.dist-info/licenses/LICENSE.txt
gen_head-1.0.0.dist-info/RECORD
